{
	"ImportPath": "github.com/wangming1993/pb2doc",
	"GoVersion": "go1.7",
	"GodepVersion": "v75",
	"Deps": [
		{
			"ImportPath": "github.com/cbroglie/mustache",
			"Rev": "6857e4b493bdb8d4b1931446eb41704aeb4c28cb"
		},
		{
			"ImportPath": "github.com/docopt/docopt-go",
			"Comment": "0.6.2",
			"Rev": "784ddc588536785e7299f7272f39101f7faccc3f"
		},
		{
			"ImportPath": "github.com/spf13/cast",
			"Rev": "27b586b42e29bec072fe7379259cc719e1289da6"
		},
		{
			"ImportPath": "github.com/spf13/jwalterweatherman",
			"Rev": "33c24e77fb80341fe7130ee7c594256ff08ccc46"
		}
	]
}
